{
  "date": "2024-03-21T06:21:28.212Z",
  "oneone": {
    "count": 20,
    "island_1": 5,
    "island_2": 3,
    "island_3": 12,
    "level_1": 4,
    "level_2": 0,
    "level_3": 0,
    "level_4": 0,
    "level_5": 0,
    "level_6": 1,
    "level_7": 0,
    "level_8": 1,
    "level_9": 1,
    "level_10": 0,
    "level_11": 0,
    "level_12": 1,
    "level_13": 0,
    "level_14": 0,
    "level_15": 0,
    "level_16": 0,
    "level_17": 0,
    "level_18": 0,
    "level_19": 0,
    "level_20": 12
  },
  "fm": {
    "count": 4990,
    "island_1": 1656,
    "island_2": 1445,
    "island_3": 1889,
    "level_1": 428,
    "level_2": 52,
    "level_3": 146,
    "level_4": 50,
    "level_5": 260,
    "level_6": 105,
    "level_7": 123,
    "level_8": 430,
    "level_9": 172,
    "level_10": 166,
    "level_11": 83,
    "level_12": 169,
    "level_13": 49,
    "level_14": 50,
    "level_15": 976,
    "level_16": 115,
    "level_17": 56,
    "level_18": 61,
    "level_19": 17,
    "level_20": 1482
  },
  "qm": {
    "count": 4990,
    "island_1": 1656,
    "island_2": 1439,
    "island_3": 1895,
    "level_1": 696,
    "level_2": 64,
    "level_3": 130,
    "level_4": 45,
    "level_5": 204,
    "level_6": 149,
    "level_7": 95,
    "level_8": 359,
    "level_9": 129,
    "level_10": 175,
    "level_11": 83,
    "level_12": 153,
    "level_13": 54,
    "level_14": 45,
    "level_15": 1269,
    "level_16": 124,
    "level_17": 52,
    "level_18": 54,
    "level_19": 26,
    "level_20": 1084
  }
}
